[{
  "SourceFile": "Gatorade/2016/KAT Venice Beach/_SLG7459.jpg",
  "FileName": "_SLG7459.jpg",
  "HierarchicalSubject": [
    "Athlete|Karl-Anthony Towns",
    "Gender|Male",
    "Gender|Female",
    "Product|Towel",
    "Number of People|Group of People (3+)",
    "Location|Los Angeles, CA (Venice Beach)",
    "Asset Type|Photography",
    "Asset Subtype|Logos",
    "Year|2016"
  ],
  "Keywords": [
    2016,
    "Female",
    "Group of People (3+)",
    "Karl-Anthony Towns",
    "Los Angeles, CA (Venice Beach)",
    "Male",
    "Original",
    "Photography",
    "Towel"
  ],
  "Subject": [
    2016,
    "Female",
    "Group of People (3+)",
    "Karl-Anthony Towns",
    "Los Angeles, CA (Venice Beach)",
    "Male",
    "Original",
    "Photography",
    "Towel"
  ],
  "CreateDate": "2016:05:25 16:47:58",
  "DateCreated": "2016:05:25",
  "DateTimeCreated": "2016:05:25 16:47:58",
  "DateTimeOriginal": "2016:05:25 16:47:58",
  "FileAccessDate": "2017:05:08 08:21:34-05:00"
},
{
  "SourceFile": "Gatorade/2016/KAT Venice Beach/_SLG7951.jpg",
  "FileName": "_SLG7951.jpg",
  "HierarchicalSubject": [
    "Product|GTQ",
    "Product|Towel",
    "Product|GTQ - FTW",
    "Number of People|Four",
    "Other Keywords|Bleachers",
    "Location|Los Angeles, CA (Venice Beach)",
    "Asset Type|Photography",
    "Asset Subtype|Original",
    "Year|2016"
  ],
  "Keywords": [
    2016,
    "Bleachers",
    "GTQ",
    "Los Angeles, CA (Venice Beach)",
    "One",
    "Original",
    "Photography",
    "Towel"
  ],
  "Subject": [
    2016,
    "Bleachers",
    "GTQ",
    "Los Angeles, CA (Venice Beach)",
    "One",
    "Original",
    "Photography",
    "Towel"
  ],
  "CreateDate": "2015:05:26 13:06:14",
  "DateCreated": "2015:05:26",
  "DateTimeCreated": "2015:05:26 13:06:14",
  "DateTimeOriginal": "2015:05:26 13:06:14",
  "FileAccessDate": "2017:05:08 08:21:34-05:00"
},
{
  "SourceFile": "Gatorade/2016/KAT Venice Beach/._SLG7985.jpg",
  "FileName": "._SLG7985.jpg",
  "Keywords": [
    2016,
    "Consumption",
    "Coolers",
    "GTQ - Fierce",
    "Karl-Anthony Towns",
    "Los Angeles, CA (Venice Beach)",
    "Male",
    "One",
    "Original",
    "Photography"
  ],
  "Subject": [
    2016,
    "Consumption",
    "Coolers",
    "GTQ - Fierce",
    "Karl-Anthony Towns",
    "Los Angeles, CA (Venice Beach)",
    "Male",
    "One",
    "Original",
    "Photography"
  ],
  "CreateDate": "2015:05:26 14:01:56",
  "DateCreated": "2015:05:26",
  "DateTimeCreated": "2015:05:26 14:01:56",
  "DateTimeOriginal": "2015:05:26 14:01:56",
  "FileAccessDate": "2017:05:08 08:21:34-05:00"
},
{
  "SourceFile": "/Volumes/VML to Bynder/Gatorade/2015/Sweat With The Best/Bryce Harper/0407_01_014.jpg",
  "FileName": "0407_01_014.jpg",
  "HierarchicalSubject": ["Gender|Male","Sport|Baseball","Marks|Game","Athlete|Bryce Harper","Number of People|One","Equipment|Batting Cage","Asset Subtype|Original","Asset Type|Photography","Year|2015"],
  "Keywords": [2015,"Baseball","Batting Cage","Bryce Harper","Game","Male","One","Original","Photography"],
  "Subject": [2015,"Baseball","Batting Cage","Bryce Harper","Game","Male","One","Original","Photography"],
  "CreateDate": "2015:02:21 10:02:11",
  "DateCreated": "2015:02:21",
  "DateTimeCreated": "2015:02:21 10:02:11-05:00",
  "DateTimeOriginal": "2015:02:21 10:02:11",
  "FileAccessDate": "2017:05:09 13:37:21-05:00"
},
{
  "SourceFile": "/Volumes/VML to Bynder/Gatorade/2016/LV High Res/D'angelo Russell/DAngelo_Russell_Gatorade-1614.jpg",
  "FileName": "DAngelo_Russell_Gatorade-1614.jpg",
  "HierarchicalSubject": ["Athlete|D'Angelo Russell","Gender|Male","Number of People|One","Marks|Practice","Concept|Locker Room","Product|Towel","Sport|Basketball","Asset Subtype|Original","Asset Type|Photography","Year|2016"],
  "Keywords": [2016,"Basketball","D'Angelo Russell","Locker Room","Male","One","Original","Photography","Practice","Towel"],
  "Subject": [2016,"Basketball","D'Angelo Russell","Locker Room","Male","One","Original","Photography","Practice","Towel"],
  "CreateDate": "2016:07:20 18:54:53",
  "DateCreated": "2016:07:20",
  "DateTimeCreated": "2016:07:20 18:54:53",
  "DateTimeOriginal": "2016:07:20 18:54:53",
  "FileAccessDate": "2017:05:09 13:38:27-05:00"
},
{
  "SourceFile": "/Volumes/VML to Bynder/Gatorade/2016/Sports Fuel/Usain Bolt/USAINBOLT-GATORADE-2015-1495.tif",
  "FileName": "USAINBOLT-GATORADE-2015-1495.tif",
  "HierarchicalSubject": ["Athlete|Usain Bolt","Gender|Male","Sport|Track","Product|Gx","Concept|Portr#ait","Concept|Sweep","Number of P!eople|One","Asset Subtype|Original","Asset Type|Photography","Year|2016"],
  "Keywords": [2016,"Gx","Male","One","Original","Photography","Portrait","Sweep","Track","Usain Bolt"],
  "Subject": [2016,"Gx","Male","One","Original","Photography","Portrait","Sweep","Track","Usain Bolt"],
  "CreateDate": "2015:12:10 22:42:22",
  "DateCreated": "2015:12:10",
  "DateTimeCreated": "2015:12:10 22:42:22",
  "DateTimeOriginal": "2015:12:10 22:42:22",
  "FileAccessDate": "2017:05:09 13:39:04-05:00"
},
{
  "SourceFile": "/Volumes/VML to Bynder/Gatorade/Graphics/Logos/Win From Within/5_WithThin # G Bolt/GAT13LOGO_WINfromWITHIN_vertG_thin_hash_fc_wht.eps",
  "FileName": "GAT13LOGO_WINfromWITHIN_vertG_thin_hash_fc_wht.eps",
  "HierarchicalSubject": ["Asset Subtype|Logos","Asset Type|Graphics","Campaign|Win From Within"],
  "Subject": ["Graphics","Logos","Win From Within"],
  "CreateDate": "7/18/13",
  "FileAccessDate": "2017:05:09 13:39:36-05:00"
},
{
  "SourceFile": "/Volumes/VML to Bynder/Gatorade/Product Renders/Soccer Formula/GFC_Or_LSE_16p9_051616.psd",
  "FileName": "GFC_Or_LSE_16p9_051616.psd",
  "HierarchicalSubject": ["Asset Type|Product Renders","Product|Soccer Formula","Shot Type|Individual Product"],
  "Keywords": ["Individual Product","Product Renders","Soccer Formula"],
  "Subject": ["Individual Product","Product Renders","Soccer Formula"],
  "CreateDate": "2016:04:14 10:04:09-07:00",
  "FileAccessDate": "2017:05:09 13:41:12-05:00"
},
{
  "SourceFile": "/Volumes/VML to Bynder/Gatorade/Product Renders/Equipment/1_gal_cooler_2010 copy.jpg",
  "FileName": "1_gal_cooler_2010 copy.jpg",
  "HierarchicalSubject": ["Product|Coolers","Asset Type|Product Renders","Product|Coolers|1 Gallon","Shot Type|Individual Product"],
  "Keywords": ["Coolers","Individual Product","Product Renders"],
  "Subject": ["Coolers","Individual Product","Product Renders"],
  "FileAccessDate": "2017:05:09 13:39:44-05:00"
},
{
  "SourceFile": "/Volumes/VML to Bynder/Gatorade/Product Renders/Equipment/3-gallon cooler copy.jpg",
  "FileName": "3-gallon cooler copy.jpg",
  "HierarchicalSubject": ["Product|Coolers","Asset Type|Product Renders","Product|Coolers|3 Gallon","Shot Type|Individual Product"],
  "Keywords": ["3 Gallon","Coolers","Individual Product","Product Renders"],
  "Subject": ["3 Gallon","Coolers","Individual Product","Product Renders"],
  "CreateDate": "2007:09:28 04:05:49",
  "DateCreated": "2007:09:28",
  "DateTimeOriginal": "2007:09:28 04:05:49",
  "FileAccessDate": "2017:05:09 13:39:44-05:00"
},
{
  "SourceFile": "/Volumes/VML to Bynder/Gatorade/Product Renders/Equipment/48qt_ice_chest_gseries copy.jpg",
  "FileName": "48qt_ice_chest_gseries copy.jpg",
  "HierarchicalSubject": ["Product|Coolers","Asset Type|Product Renders","Product|Coolers|Ice Chest","Shot Type|Individual Product"],
  "Keywords": ["Coolers","Individual Product","Product Renders"],
  "Subject": ["Coolers","Individual Product","Product Renders"],
  "FileAccessDate": "2017:05:09 13:39:44-05:00"
}
]
